simple_back/__init__.py
simple_back/backtester.py
simple_back/data_providers.py
simple_back/exceptions.py
simple_back/fees.py
simple_back/metrics.py
simple_back/strategy.py
simple_back/utils.py
simple_back-0.6.3.dist-info/LICENSE
simple_back-0.6.3.dist-info/WHEEL
simple_back-0.6.3.dist-info/METADATA
simple_back-0.6.3.dist-info/RECORD
