Metadata-Version: 2.1
Name: simple-back
Version: 0.6.3
Summary: A backtester with minimal setup and sensible defaults.
Author: Christoph Minixhofer
Author-email: christoph.minixhofer@gmail.com
Requires-Python: >=3.6.9,<4.0.0
Classifier: Programming Language :: Python :: 3
Classifier: Programming Language :: Python :: 3.7
Classifier: Programming Language :: Python :: 3.8
Classifier: Programming Language :: Python :: 3.9
Requires-Dist: beautifulsoup4 (>=4.9.1,<5.0.0)
Requires-Dist: diskcache (>=4.1.0,<5.0.0)
Requires-Dist: memoization (>=0.3.1,<0.4.0)
Requires-Dist: numpy (>=1.18.4,<2.0.0)
Requires-Dist: pandas (>=1.0.3,<2.0.0)
Requires-Dist: pandas_market_calendars (>=1.3.5,<2.0.0)
Requires-Dist: pytz (>=2020.1,<2021.0)
Requires-Dist: requests_html (>=0.10.0,<0.11.0)
Requires-Dist: tabulate (>=0.8.7,<0.9.0)
Requires-Dist: yahoo_fin (>=0.8.5,<0.9.0)
